{
  "章回信息": {
    "标题": "第六十四回 包青天奉旨审命案 白芸瑞公堂诉曲直",
    "章节": "064"
  },
  "详细版事件列表": [
    "仁宗皇帝传包拯上殿，命其审理三国舅庞虎被杀案，被告指向白芸瑞",
    "包拯升堂审案，新娘李玉秋当堂指认白芸瑞为凶手",
    "白芸瑞辩解称被陌生人骗至四喜堂，后追赶神秘人到城外四十里",
    "从白芸瑞住处搜出新娘丢失的首饰二十一件，人证物证俱全",
    "包拯大怒，下令用狗头铡处死白芸瑞",
    "关键时刻房书安喊"刀下留人"，请求传讯四喜堂和茶汤馆证人",
    "证人证实白芸瑞所言属实，庞虎被杀时白芸瑞不在现场",
    "包拯将白芸瑞暂时收监，等待进一步调查，庞吉不满但无奈"
  ],
  "简化版事件列表": [
    "包拯奉旨审案",
    "白芸瑞被指认为凶手并搜出赃物",
    "包拯下令处斩白芸瑞",
    "房书安喊刀下留人，找证人证实白芸瑞不在场",
    "白芸瑞暂时收监"
  ],
  "极简版事件列表": [
    "包拯审案，白芸瑞被栽赃",
    "搜出赃物，包拯大怒",
    "房书安救场，证人作证",
    "白芸瑞收监待查"
  ],
  "绘图提示词": "开封府大堂，包拯（黑脸，穿官服）坐公位，拍案大怒；堂下白芸瑞（英俊青年，被捆绑）口喊冤枉；旁边房书安（大脑袋细脖子）跪倒喊"刀下留人"；庞吉（白须老人）和李天祥（官员）在旁听席上；蒋平、展昭等站班；地上有狗头铡和刚搜出的首饰；堂内气氛紧张，生死攸关。"
}