{
    "章回信息": "第七十五回 闯重围群雄脱险境 救八王老房下苦工",
    "详细版事件列表": [
        "郭长达命令弓箭手围攻徐良等人，徐良、白芸瑞当先开路，众人边打边撤退",
        "欧阳春和韩天锦在东北角破墙，众人由此突围而出，五百小道士追击",
        "蒋平安排欧阳春、徐良、白芸瑞、钟林四人断后，众人进入树林脱险，郭长达收兵",
        "众人回到开封府，大多受伤，包大人着急，徐良责备房书安保护八王不力",
        "房书安决定单独前往莲花观探听八王下落，在路上遇到上吊老人刘老五并救下",
        "刘老五讲述儿媳妇邹氏与郭长达有不正当关系，房书安决定利用此机会捉拿郭长达",
        "房书安在杂货铺观察环境，见到邹氏，了解后院情况，计划晚上行动"
    ],
    "简化版事件列表": [
        "郭长达围攻徐良等人，众人突围而出",
        "房书安自责并决定前往莲花观探查",
        "房书安救下上吊老人刘老五，得知郭长达与刘老五儿媳妇邹氏有染",
        "房书安计划利用此机会捉拿郭长达"
    ],
    "极简版事件列表": [
        "众人突围",
        "房书安探查",
        "发现郭长达丑事",
        "计划捉拿"
    ],
    "绘图提示词": "刘家集杂货铺前，房书安（大脑袋，没鼻子，穿公差服）站在门口向内张望；门内柜台后站着邹氏（年轻女子，高绾云鬓，尖下颏，月牙眼，带酒坑，衣着光鲜）；杂货铺挂着幌子和'刘家集杂货铺'的招牌；周围是山村景象，有几位农民在远处；房书安表情警惕，手里拿着刚买的花生仁儿；邹氏表情妩媚，似笑非笑；整个场景充满了房书安探查和计划行动的紧张感"
}